{
  "name": "sparse_matrix",
  "version": "0.6.0",
  "repo": "goodcleanfun/sparse_matrix",
  "description": "Compressed dynamic sparse matrices with efficient heap-based sparse multiply",
  "keywords": ["matrix", "sparse", "array", "numeric"],
  "dependencies": {
    "goodcleanfun/vector_ops": "*",
    "goodcleanfun/file_utils": "*",
    "goodcleanfun/hashes": "*",
    "goodcleanfun/heap": "*",
    "goodcleanfun/sorting": "*",
    "goodcleanfun/num_array": "*"
  },
  "development": {
    "silentbicycle/greatest": "*"
  },
  "license": "MIT",
  "src": [
    "src/compressed.h",
    "src/csr.h",
    "src/double_csr.h",
    "src/float_csr.h"
  ]
}

